.gitignore
LICENSE.txt
README.rst
setup.py
tox.ini
docs/api.rst
docs/conf.py
docs/index.rst
docs/quickstart.rst
docs/server.cas.rst
docs/server.rst
examples/async.py
examples/simple.py
src/channel_access.server.egg-info/PKG-INFO
src/channel_access.server.egg-info/SOURCES.txt
src/channel_access.server.egg-info/dependency_links.txt
src/channel_access.server.egg-info/requires.txt
src/channel_access.server.egg-info/top_level.txt
src/channel_access/server/__init__.py
src/channel_access/server/cas/async.cpp
src/channel_access/server/cas/async.hpp
src/channel_access/server/cas/cas.cpp
src/channel_access/server/cas/cas.hpp
src/channel_access/server/cas/convert.cpp
src/channel_access/server/cas/convert.hpp
src/channel_access/server/cas/numpy.hpp
src/channel_access/server/cas/pv.cpp
src/channel_access/server/cas/pv.hpp
src/channel_access/server/cas/server.cpp
src/channel_access/server/cas/server.hpp
tests/__init__.py
tests/common.py
tests/conftest.py
tests/test_attributes.py
tests/test_get.py
tests/test_handler.py
tests/test_limits.py
tests/test_misc.py
tests/test_put.py